usr/share/bash-completion/completions/virtme-ng-prompt
usr/share/bash-completion/completions/vng-prompt
virtme/__init__.py
virtme/architectures.py
virtme/cpiowriter.py
virtme/mkinitramfs.py
virtme/modfinder.py
virtme/qemu_helpers.py
virtme/resources.py
virtme/util.py
virtme/virtmods.py
virtme/commands/__init__.py
virtme/commands/configkernel.py
virtme/commands/mkinitramfs.py
virtme/commands/run.py
virtme/guest/__init__.py
virtme/guest/virtme-init
virtme/guest/virtme-snapd-script
virtme/guest/virtme-sound-script
virtme/guest/virtme-sshd-script
virtme/guest/virtme-udhcpc-script
virtme/guest/bin/virtme-ng-init
virtme_ng/__init__.py
virtme_ng/mainline.py
virtme_ng/run.py
virtme_ng/spinner.py
virtme_ng/utils.py
virtme_ng/version.py
virtme_ng-1.38.data/scripts/virtme-prep-kdir-mods
virtme_ng-1.38.data/scripts/virtme-ssh-proxy
virtme_ng-1.38.dist-info/licenses/LICENSE
virtme_ng-1.38.dist-info/METADATA
virtme_ng-1.38.dist-info/WHEEL
virtme_ng-1.38.dist-info/entry_points.txt
virtme_ng-1.38.dist-info/top_level.txt
virtme_ng-1.38.dist-info/RECORD
