Metadata-Version: 2.4
Name: virtme-ng
Version: 1.38
Summary: Build and run a kernel inside a virtualized snapshot of your live system
Home-page: https://github.com/arighi/virtme-ng
Author: Andrea Righi
Author-email: arighi@nvidia.com
License: GPL-2.0-only
Classifier: Environment :: Console
Classifier: Intended Audience :: Developers
Classifier: Intended Audience :: System Administrators
Classifier: Operating System :: POSIX :: Linux
Requires-Python: >=3.8
License-File: LICENSE
Requires-Dist: argcomplete
Requires-Dist: requests
Requires-Dist: setuptools
Dynamic: author
Dynamic: author-email
Dynamic: classifier
Dynamic: description
Dynamic: description-content-type
Dynamic: home-page
Dynamic: license
Dynamic: license-file
Dynamic: requires-dist
Dynamic: summary
